django_minify_html/__init__.py
django_minify_html/apps.py
django_minify_html/decorators.py
django_minify_html/middleware.py
django_minify_html/py.typed
django_minify_html-1.13.0.dist-info/licenses/LICENSE
django_minify_html-1.13.0.dist-info/METADATA
django_minify_html-1.13.0.dist-info/WHEEL
django_minify_html-1.13.0.dist-info/top_level.txt
django_minify_html-1.13.0.dist-info/RECORD
